{
  "stakePool": {
    "account": {
      "data": "{\"type\":\"Buffer\",\"data\":[121,34,206,21,79,127,255,28,253,129,0,0,0,0,0,0,0,108,117,139,35,229,98,85,2,141,10,129,188,205,11,147,230,79,207,58,97,48,18,247,247,182,18,146,204,147,109,76,207,1,0,0,0,165,203,143,157,254,188,182,138,211,128,1,230,226,88,150,178,137,42,14,213,38,45,88,128,121,73,203,66,36,202,202,115,0,0,0,0,0,6,0,0,0,83,84,65,75,69,68,0,0,0,0,0,0,0,0,0,0,0,0,0,0,0,0,0,0,0,0,0,0,0,0,0,0,0,0,0,0,0,0,0,0,0,0,0,0,0,0,0,0,0,0,0,0,0,0,0,0,0,0,0,0,0,0,0,0,0,0,0,0,0,0,0,0,0,0,0,0,0,0,0,0,0,0,0,0,0,0,0,0,0,0,0,0,0,0,0,0,0,0,0,0,0,0,0,0,0,0,0,0,0,0,0,0,0,0,0,0,0,0,0,0,0,0,0,0,0,0,0,0,0,0,0,0,0,0,0,0,0,0,0,0,0,0,0,0,0,0,0,0,0,0,0,0,0,0,0,0,0,0,0,0,0,0,0,0,0,0,0,0,0,0,0,0,0,0,0,0,0,0,0,0,0,0,0,0,0,0,0,0,0,0,0,0,0,0,0,0,0,0,0,0,0,0,0,0,0,0,0,0,0,0,0,0,0,0,0,0,0,0,0,0,0,0,0,0,0,0,0,0,0,0,0,0,0,0,0,0,0,0,0,0,0,0,0,0,0,0,0,0,0,0,0,0,0,0,0,0,0,0,0,0,0,0,0,0,0,0,0,0,0,0,0,0,0,0,0,0,0,0,0,0,0,0,0,0,0,0,0,0,0,0,0,0,0,0,0,0,0,0,0,0,0,0,0,0,0,0,0,0,0,0,0,0,0,0,0,0,0,0,0,0,0,0,0,0,0,0,0,0,0,0,0,0,0,0,0,0,0,0,0,0,0,0,0,0,0,0,0,0,0,0,0,0,0,0,0,0,0,0,0,0,0,0,0,0,0,0,0,0,0,0,0,0]}",
      "executable": false,
      "lamports": 4134240,
      "owner": "stkBL96RZkjY5ine4TvPihGqW8UHJfch2cokjAPzV8i",
      "rentEpoch": 361
    },
    "pubkey": "86Hn61WwNuv4hizUHE4ve9jgVyKeNwxdkCmXBQVAaBrg",
    "parsed": {
      "bump": "253",
      "identifier": "129",
      "authority": "8JNzGkQWyXa6yt7SDZBrKqSgQsJMDQGFYdLcc7vTBu1p",
      "requiresCreators": "CACJRw5TNd1AMC15QAunt8yMHAUBbcCKtoeQUWujrgQz",
      "requiresCollections": "",
      "requiresAuthorization": "false",
      "overlayText": "STAKED",
      "imageUri": "",
      "resetOnStake": "false",
      "totalStaked": "0"
    }
  },
  "rewardDistributor": {
    "timestamp": 1693962586045,
    "pubkey": "8uZJurZxfkdcPs2ryp8kGtAKXMW1UKsq2U95akM1sSgF",
    "data": "{\"type\":\"Buffer\",\"data\":[215,10,217,199,104,194,97,227,255,105,92,174,200,31,152,131,245,202,50,6,239,154,180,43,138,125,109,136,201,106,204,131,182,158,10,4,96,34,185,19,161,2,108,117,139,35,229,98,85,2,141,10,129,188,205,11,147,230,79,207,58,97,48,18,247,247,182,18,146,204,147,109,76,207,248,46,126,1,99,27,64,31,193,95,84,237,23,93,154,146,102,254,81,245,113,105,93,80,177,172,172,151,10,247,10,175,0,202,154,59,0,0,0,0,60,0,0,0,0,0,0,0,0,0,0,0,0,0,0,0,0,254,124,108,4,0,0,0,0,0,0,0,0,0,0,0,0,1,0,0,0,0,0,0,0,0,0,0,0,0,0,0,0,0,0,0,0,0,0,0,0,0,0,0,0,0,0,0,0,0,0,0,0,0,0,0,0,0,0,0,0,0,0,0,0,0,0,0,0,0,0,0,0,0,0,0,0,0,0,0,0,0,0,0,0,0,0,0,0,0,0,0,0,0,0,0,0,0,0,0,0,0,0,0,0,0,0,0,0,0]}",
    "executable": false,
    "lamports": 2561280,
    "owner": "rwdNPNPS6zNvtF6FMvaxPRjzu2eC51mXaDT9rmWsojp",
    "rentEpoch": 361,
    "type": "rewardDistributor",
    "parsed": {
      "bump": "255",
      "stakePool": "86Hn61WwNuv4hizUHE4ve9jgVyKeNwxdkCmXBQVAaBrg",
      "kind": "2",
      "authority": "8JNzGkQWyXa6yt7SDZBrKqSgQsJMDQGFYdLcc7vTBu1p",
      "rewardMint": "HhoEAbSPui6EncKntxdToz8cPPLtacgshfKXUjzRYBUr",
      "rewardAmount": "1000000000",
      "rewardDurationSeconds": "60",
      "rewardsIssued": "19000000000",
      "defaultMultiplier": "1",
      "multiplierDecimals": "0"
    }
  },
  "rewardDistributorTokenAccount": {
    "address": "8fBhFj1jTeeRiFtLb6iqmGdMoCE5XuJWuko2DxMXy9yE",
    "mint": "HhoEAbSPui6EncKntxdToz8cPPLtacgshfKXUjzRYBUr",
    "owner": "8uZJurZxfkdcPs2ryp8kGtAKXMW1UKsq2U95akM1sSgF",
    "amount": "1000000000",
    "delegate": null,
    "delegatedAmount": "0",
    "isInitialized": true,
    "isFrozen": false,
    "isNative": false,
    "closeAuthority": null,
    "tlvData": {
      "type": "Buffer",
      "data": "[]"
    }
  },
  "stakeEntries": [
    {
      "account": {
        "data": "{\"type\":\"Buffer\",\"data\":[187,127,9,35,155,68,86,40,255,105,92,174,200,31,152,131,245,202,50,6,239,154,180,43,138,125,109,136,201,106,204,131,182,158,10,4,96,34,185,19,161,0,0,0,0,0,0,0,0,32,88,114,144,156,110,235,124,91,19,242,184,89,93,54,155,86,155,189,58,211,114,147,65,97,54,35,128,233,251,207,230,0,0,0,0,0,0,0,0,0,0,0,0,0,0,0,0,0,0,0,0,0,0,0,0,0,0,0,0,0,0,0,0,0,104,196,189,98,0,0,0,0,47,2,0,0,0,0,0,0,0,0,0,0,0,0,0,0,0,0,0,0,0,0,0,0,0,0,0,0,0,0,0,0,0,0,0,0,0,0,0,0,0,0,0,0,0,0,0,0,0,0,0,0,0,0,0,0,0,0,0,0,0,0,0,0,0,0,0,0,0,0,0,0,0,0,0,0,0,0]}",
        "executable": false,
        "lamports": 2282880,
        "owner": "stkBL96RZkjY5ine4TvPihGqW8UHJfch2cokjAPzV8i",
        "rentEpoch": 361
      },
      "pubkey": "9GdChepyj9kczn6t6xwWFYGhL3MenwVtgBFnWKUCV42o",
      "parsed": {
        "bump": "255",
        "pool": "86Hn61WwNuv4hizUHE4ve9jgVyKeNwxdkCmXBQVAaBrg",
        "amount": "0",
        "originalMint": "3BGGeUvaRyBu4qoVStT9wtPfakjVjGq3gqmvvWvdFMHf",
        "originalMintClaimed": "false",
        "lastStaker": "11111111111111111111111111111111",
        "lastStakedAt": "1656603752",
        "totalStakeSeconds": "559",
        "stakeMintClaimed": "false",
        "kind": "0"
      }
    },
    {
      "account": {
        "data": "{\"type\":\"Buffer\",\"data\":[187,127,9,35,155,68,86,40,254,105,92,174,200,31,152,131,245,202,50,6,239,154,180,43,138,125,109,136,201,106,204,131,182,158,10,4,96,34,185,19,161,0,0,0,0,0,0,0,0,245,106,231,27,111,75,220,81,155,193,251,97,221,147,49,143,99,27,100,80,125,171,11,36,149,189,222,8,38,122,210,32,0,0,0,0,0,0,0,0,0,0,0,0,0,0,0,0,0,0,0,0,0,0,0,0,0,0,0,0,0,0,0,0,0,4,158,189,98,0,0,0,0,126,2,0,0,0,0,0,0,0,0,0,0,0,0,0,0,0,0,0,0,0,0,0,0,0,0,0,0,0,0,0,0,0,0,0,0,0,0,0,0,0,0,0,0,0,0,0,0,0,0,0,0,0,0,0,0,0,0,0,0,0,0,0,0,0,0,0,0,0,0,0,0,0,0,0,0,0,0]}",
        "executable": false,
        "lamports": 2282880,
        "owner": "stkBL96RZkjY5ine4TvPihGqW8UHJfch2cokjAPzV8i",
        "rentEpoch": 361
      },
      "pubkey": "CFyRQsEkWEx83m56abkWi6VGVJ5RLGgE7MYC3AonMcrg",
      "parsed": {
        "bump": "254",
        "pool": "86Hn61WwNuv4hizUHE4ve9jgVyKeNwxdkCmXBQVAaBrg",
        "amount": "0",
        "originalMint": "HX1S1t7s2qYqEN4PeB8MDvjwXXceMaVRgAGsTqUPyTsd",
        "originalMintClaimed": "false",
        "lastStaker": "11111111111111111111111111111111",
        "lastStakedAt": "1656593924",
        "totalStakeSeconds": "638",
        "stakeMintClaimed": "false",
        "kind": "0"
      }
    },
    {
      "account": {
        "data": "{\"type\":\"Buffer\",\"data\":[187,127,9,35,155,68,86,40,254,105,92,174,200,31,152,131,245,202,50,6,239,154,180,43,138,125,109,136,201,106,204,131,182,158,10,4,96,34,185,19,161,0,0,0,0,0,0,0,0,111,90,102,212,196,235,238,71,70,230,128,159,156,40,55,172,195,247,249,68,228,154,212,247,203,21,244,59,60,164,120,54,0,0,0,0,0,0,0,0,0,0,0,0,0,0,0,0,0,0,0,0,0,0,0,0,0,0,0,0,0,0,0,0,0,65,158,189,98,0,0,0,0,191,1,0,0,0,0,0,0,0,0,0,0,0,0,0,0,0,0,1,159,222,118,53,177,84,153,177,50,252,222,79,12,172,228,64,238,112,226,88,15,200,253,45,77,224,147,172,140,71,8,156,0,0,0,0,0,0,0,0,0,0,0,0,0,0,0,0,0,0,0,0,0,0,0,0,0,0,0]}",
        "executable": false,
        "lamports": 2282880,
        "owner": "stkBL96RZkjY5ine4TvPihGqW8UHJfch2cokjAPzV8i",
        "rentEpoch": 361
      },
      "pubkey": "FG5LnXGpf5Ewez8YkNP5LTjbY3rmfc4gk8cjm2nTKLei",
      "parsed": {
        "bump": "254",
        "pool": "86Hn61WwNuv4hizUHE4ve9jgVyKeNwxdkCmXBQVAaBrg",
        "amount": "0",
        "originalMint": "8VgCxX8jhpDk5BgXzexQ8yWciRcKj4SSTURkr7raJzyj",
        "originalMintClaimed": "false",
        "lastStaker": "11111111111111111111111111111111",
        "lastStakedAt": "1656593985",
        "totalStakeSeconds": "447",
        "stakeMintClaimed": "false",
        "kind": "0",
        "stakeMint": "Bm4a5KWzTKvrX45Bv2GHGkZ8xKW15c2cf1ihYP7mr1R5"
      }
    }
  ],
  "rewardEntries": [
    {
      "account": {
        "data": "{\"type\":\"Buffer\",\"data\":[208,191,173,14,213,84,179,162,253,122,222,36,23,142,224,246,208,202,25,209,160,220,117,96,10,159,210,211,106,28,34,226,166,161,80,250,156,120,164,197,196,117,120,138,208,234,13,57,121,135,49,14,180,190,49,245,24,217,113,135,156,228,247,92,161,32,6,217,93,64,162,204,248,28,2,0,0,0,0,0,0,0,0,0,0,0,0,0,0,1,0,0,0,0,0,0,0,0,0,0,0,0,0,0,0,0,0,0,0,0,0,0,0,0,0,0,0,0,0,0,0,0,0,0,0,0,0,0,0,0,0,0,0,0,0,0,0,0,0,0,0,0,0,0,0,0,0,0,0,0,0,0,0,0,0,0,0,0,0,0,0,0,0,0,0,0,0,0]}",
        "executable": false,
        "lamports": 2060160,
        "owner": "rwdNPNPS6zNvtF6FMvaxPRjzu2eC51mXaDT9rmWsojp",
        "rentEpoch": 361
      },
      "pubkey": "87uf4Da4VNdGUv5r5U4TtruhkJD5CnoZ1qTLWTFztYfM",
      "parsed": {
        "bump": "253",
        "stakeEntry": "9GdChepyj9kczn6t6xwWFYGhL3MenwVtgBFnWKUCV42o",
        "rewardDistributor": "8uZJurZxfkdcPs2ryp8kGtAKXMW1UKsq2U95akM1sSgF",
        "rewardSecondsReceived": "540",
        "multiplier": "1"
      }
    },
    {
      "account": {
        "data": "{\"type\":\"Buffer\",\"data\":[208,191,173,14,213,84,179,162,255,211,224,60,212,223,36,245,251,189,133,126,159,186,122,149,103,4,24,183,55,136,80,188,57,223,129,7,142,22,68,106,7,117,120,138,208,234,13,57,121,135,49,14,180,190,49,245,24,217,113,135,156,228,247,92,161,32,6,217,93,64,162,204,248,0,0,0,0,0,0,0,0,0,0,0,0,0,0,0,0,1,0,0,0,0,0,0,0,0,0,0,0,0,0,0,0,0,0,0,0,0,0,0,0,0,0,0,0,0,0,0,0,0,0,0,0,0,0,0,0,0,0,0,0,0,0,0,0,0,0,0,0,0,0,0,0,0,0,0,0,0,0,0,0,0,0,0,0,0,0,0,0,0,0,0,0,0,0,0]}",
        "executable": false,
        "lamports": 2060160,
        "owner": "rwdNPNPS6zNvtF6FMvaxPRjzu2eC51mXaDT9rmWsojp",
        "rentEpoch": 361
      },
      "pubkey": "DWiyc784DDmCLKfo2SWWiPaYXHNioEJGXNPgnTS8FwjN",
      "parsed": {
        "bump": "255",
        "stakeEntry": "FG5LnXGpf5Ewez8YkNP5LTjbY3rmfc4gk8cjm2nTKLei",
        "rewardDistributor": "8uZJurZxfkdcPs2ryp8kGtAKXMW1UKsq2U95akM1sSgF",
        "rewardSecondsReceived": "0",
        "multiplier": "1"
      }
    },
    {
      "account": {
        "data": "{\"type\":\"Buffer\",\"data\":[208,191,173,14,213,84,179,162,254,167,70,123,153,246,8,210,81,231,201,82,0,84,188,134,167,6,96,230,77,188,147,34,30,233,144,231,50,141,15,255,29,117,120,138,208,234,13,57,121,135,49,14,180,190,49,245,24,217,113,135,156,228,247,92,161,32,6,217,93,64,162,204,248,88,2,0,0,0,0,0,0,0,0,0,0,0,0,0,0,1,0,0,0,0,0,0,0,0,0,0,0,0,0,0,0,0,0,0,0,0,0,0,0,0,0,0,0,0,0,0,0,0,0,0,0,0,0,0,0,0,0,0,0,0,0,0,0,0,0,0,0,0,0,0,0,0,0,0,0,0,0,0,0,0,0,0,0,0,0,0,0,0,0,0,0,0,0,0]}",
        "executable": false,
        "lamports": 2060160,
        "owner": "rwdNPNPS6zNvtF6FMvaxPRjzu2eC51mXaDT9rmWsojp",
        "rentEpoch": 361
      },
      "pubkey": "HdL5BgxmhmGvRKjb1H4BvEg56ReMRz7FwpRX61ez4aHi",
      "parsed": {
        "bump": "254",
        "stakeEntry": "CFyRQsEkWEx83m56abkWi6VGVJ5RLGgE7MYC3AonMcrg",
        "rewardDistributor": "8uZJurZxfkdcPs2ryp8kGtAKXMW1UKsq2U95akM1sSgF",
        "rewardSecondsReceived": "600",
        "multiplier": "1"
      }
    }
  ]
}
