{
  "stakePool": {
    "account": {
      "data": "{\"type\":\"Buffer\",\"data\":[121,34,206,21,79,127,255,28,255,92,1,0,0,0,0,0,0,65,175,1,112,40,40,120,197,149,156,181,52,109,181,236,15,2,64,38,165,216,89,38,51,133,227,21,163,213,246,243,124,1,0,0,0,227,178,219,165,12,6,110,50,151,253,230,4,78,3,124,108,66,129,69,200,71,171,200,196,25,189,130,84,110,52,106,199,1,0,0,0,175,145,7,16,238,73,168,79,64,86,117,153,157,253,36,49,94,53,182,136,228,172,242,177,130,15,231,23,48,11,155,181,1,6,0,0,0,83,84,65,75,69,68,0,0,0,0,0,2,0,0,0,1,0,0,0,0,1,0,0,0,0,1,128,126,146,110,0,0,0,0,0,0,0,0,0,0,0,0,0,0,0,0,0,0,0,0,0,0,0,0,0,0,0,0,0,0,0,0,0,0,0,0,0,0,0,0,0,0,0,0,0,0,0,0,0,0,0,0,0,0,0,0,0,0,0,0,0,0,0,0,0,0,0,0,0,0,0,0,0,0,0,0,0,0,0,0,0,0,0,0,0,0,0,0,0,0,0,0,0,0,0,0,0,0,0,0,0,0,0,0,0,0,0,0,0,0,0,0,0,0,0,0,0,0,0,0,0,0,0,0,0,0,0,0,0,0,0,0,0,0,0,0,0,0,0,0,0,0,0,0,0,0,0,0,0,0,0,0,0,0,0,0,0,0,0,0,0,0,0,0,0,0,0,0,0,0,0,0,0,0,0,0,0,0,0,0,0,0,0,0,0,0,0,0,0,0,0,0,0,0,0,0,0,0,0,0,0,0,0,0,0,0,0,0,0,0,0,0,0,0,0,0,0,0,0,0,0,0,0,0,0,0,0,0,0,0,0,0,0,0,0,0,0,0,0,0,0,0,0,0,0,0,0,0,0,0,0,0,0,0,0,0,0,0,0,0,0,0,0,0,0,0,0,0,0,0,0,0,0,0,0,0,0,0,0,0,0,0,0,0,0,0,0,0,0,0,0,0,0,0,0,0,0,0,0,0,0,0,0,0,0,0,0,0,0,0]}",
      "executable": false,
      "lamports": 4134240,
      "owner": "stkBL96RZkjY5ine4TvPihGqW8UHJfch2cokjAPzV8i",
      "rentEpoch": 371,
      "space": 466
    },
    "pubkey": "5LgjNs1E8umkLTcM3kfxYaDtyvECu9zFnfn14FAdsYVe",
    "parsed": {
      "bump": "255",
      "identifier": "348",
      "authority": "5RQH2As1y5HE1pAF1bTUYtMoUtmqhj4zkvXxXMvkZ1tX",
      "requiresCreators": "GKqjMjkezuUqgyDhh8t58ebrmcix31QksChyWmN2EBfC",
      "requiresCollections": "CpLcPu1zBHuNphQCSVUsdLvJ9WSvwyRE6bX511Rqq1n4",
      "requiresAuthorization": "true",
      "overlayText": "STAKED",
      "imageUri": "",
      "resetOnStake": "false",
      "totalStaked": "2",
      "cooldownSeconds": "0",
      "minStakeSeconds": "0",
      "endDate": "1855094400"
    }
  },
  "rewardDistributor": {
    "timestamp": 1693168017573,
    "pubkey": "CQMvarh6JgmbGwyZyMTP9RSLk71Q4AQsKDyk556r9JYP",
    "data": "{\"type\":\"Buffer\",\"data\":[215,10,217,199,104,194,97,227,254,64,121,180,231,38,80,70,221,15,100,166,141,166,66,156,251,75,47,217,16,56,178,125,36,221,251,123,42,104,134,27,137,2,65,175,1,112,40,40,120,197,149,156,181,52,109,181,236,15,2,64,38,165,216,89,38,51,133,227,21,163,213,246,243,124,23,194,150,148,5,194,36,145,197,246,70,56,242,166,159,246,166,200,215,122,151,164,109,163,206,111,244,21,181,139,177,253,0,228,11,84,2,0,0,0,60,0,0,0,0,0,0,0,0,0,0,0,0,0,0,0,0,0,0,0,0,0,0,0,0,0,0,0,0,0,0,0,0,1,0,0,0,0,0,0,0,0,0,0,0,0,0,0,0,0,0,0,0,0,0,0,0,0,0,0,0,0,0,0,0,0,0,0,0,0,0,0,0,0,0,0,0,0,0,0,0,0,0,0,0,0,0,0,0,0,0,0,0,0,0,0,0,0,0,0,0,0,0,0,0,0,0,0,0,0,0,0,0,0,0,0,0,0,0,0,0,0,0,0,0,0]}",
    "executable": false,
    "lamports": 2561280,
    "owner": "rwdNPNPS6zNvtF6FMvaxPRjzu2eC51mXaDT9rmWsojp",
    "rentEpoch": 371,
    "space": 240,
    "type": "rewardDistributor",
    "parsed": {
      "bump": "254",
      "stakePool": "5LgjNs1E8umkLTcM3kfxYaDtyvECu9zFnfn14FAdsYVe",
      "kind": "2",
      "authority": "5RQH2As1y5HE1pAF1bTUYtMoUtmqhj4zkvXxXMvkZ1tX",
      "rewardMint": "2bkUNFnuYN1hFMfemrTgDuHdMRpEWUp8y3xys4cBRdbz",
      "rewardAmount": "10000000000",
      "rewardDurationSeconds": "60",
      "rewardsIssued": "0",
      "defaultMultiplier": "1",
      "multiplierDecimals": "0"
    }
  },
  "rewardDistributorTokenAccount": {
    "address": "GMwsd6SecB2ABLs7eDB9ZrzVuZPeV9b9hk5oyLbD24uz",
    "mint": "2bkUNFnuYN1hFMfemrTgDuHdMRpEWUp8y3xys4cBRdbz",
    "owner": "CQMvarh6JgmbGwyZyMTP9RSLk71Q4AQsKDyk556r9JYP",
    "amount": "1000000000000000",
    "delegate": null,
    "delegatedAmount": "0",
    "isInitialized": true,
    "isFrozen": false,
    "isNative": false,
    "closeAuthority": null,
    "tlvData": {
      "type": "Buffer",
      "data": "[]"
    }
  },
  "stakeEntries": [],
  "rewardEntries": []
}
