{
  "stakePool": {
    "account": {
      "data": "{\"type\":\"Buffer\",\"data\":[121,34,206,21,79,127,255,28,254,2,3,0,0,0,0,0,0,31,40,27,111,14,239,220,244,107,143,212,76,158,65,93,248,189,182,64,139,163,48,47,206,33,79,207,206,84,34,86,3,1,0,0,0,112,91,114,238,124,137,230,182,104,130,25,32,37,185,170,16,237,215,248,105,22,187,169,105,226,78,103,135,178,105,252,141,0,0,0,0,0,0,0,0,0,0,0,0,0,0,0,0,0,0,1,32,78,0,0,0,1,128,81,51,100,0,0,0,0,1,0,0,0,0,0,0,0,0,0,0,0,0,0,0,0,0,0,0,0,0,0,0,0,0,0,0,0,0,0,0,0,0,0,0,0,0,0,0,0,0,0,0,0,0,0,0,0,0,0,0,0,0,0,0,0,0,0,0,0,0,0,0,0,0,0,0,0,0,0,0,0,0,0,0,0,0,0,0,0,0,0,0,0,0,0,0,0,0,0,0,0,0,0,0,0,0,0,0,0,0,0,0,0,0,0,0,0,0,0,0,0,0,0,0,0,0,0,0,0,0,0,0,0,0,0,0,0,0,0,0,0,0,0,0,0,0,0,0,0,0,0,0,0,0,0,0,0,0,0,0,0,0,0,0,0,0,0,0,0,0,0,0,0,0,0,0,0,0,0,0,0,0,0,0,0,0,0,0,0,0,0,0,0,0,0,0,0,0,0,0,0,0,0,0,0,0,0,0,0,0,0,0,0,0,0,0,0,0,0,0,0,0,0,0,0,0,0,0,0,0,0,0,0,0,0,0,0,0,0,0,0,0,0,0,0,0,0,0,0,0,0,0,0,0,0,0,0,0,0,0,0,0,0,0,0,0,0,0,0,0,0,0,0,0,0,0,0,0,0,0,0,0,0,0,0,0,0,0,0,0,0,0,0,0,0,0,0,0,0,0,0,0,0,0,0,0,0,0,0,0,0,0,0,0,0,0,0,0,0,0,0,0,0,0,0,0,0,0,0,0,0,0,0,0,0,0,0,0,0,0,0,0,0,0,0,0,0,0,0,0,0,0,0,0,0,0,0]}",
      "executable": false,
      "lamports": 4134240,
      "owner": "stkBL96RZkjY5ine4TvPihGqW8UHJfch2cokjAPzV8i",
      "rentEpoch": 0
    },
    "pubkey": "HkX51yR2Xw83dnjxqdMgTp3GaAdw4FoQkwr2S3yvehdc",
    "parsed": {
      "bump": "254",
      "identifier": "770",
      "authority": "36d7Mj53uUVjtFmZYGkGMvxXNiuehDSCKPxvE2RbjaNn",
      "requiresCreators": "8ZbYKnGrQGUveCGWtY6A7dsayNBo1QiL14GxMggbd6Xn",
      "requiresCollections": "",
      "requiresAuthorization": "false",
      "overlayText": "",
      "imageUri": "",
      "resetOnStake": "false",
      "totalStaked": "0",
      "cooldownSeconds": "20000",
      "endDate": "1681084800",
      "doubleOrResetEnabled": "false"
    }
  },
  "rewardDistributor": null,
  "rewardDistributorTokenAccount": null,
  "stakeEntries": [
    {
      "account": {
        "data": "{\"type\":\"Buffer\",\"data\":[187,127,9,35,155,68,86,40,255,248,224,247,11,249,244,66,146,78,181,216,225,80,113,203,203,11,233,104,138,222,154,125,82,93,212,26,179,132,213,59,3,0,0,0,0,0,0,0,0,118,71,246,233,226,30,221,170,108,111,177,223,33,46,184,168,161,30,112,157,8,52,57,253,3,45,207,213,99,142,27,146,0,0,0,0,0,0,0,0,0,0,0,0,0,0,0,0,0,0,0,0,0,0,0,0,0,0,0,0,0,0,0,0,0,208,130,190,99,0,0,0,0,179,113,139,0,0,0,0,0,0,0,0,0,0,0,0,0,0,0,0,0,1,209,156,158,100,0,0,0,0,0,0,0,0,0,0,0,0,0,0,0,0,0,0,0,0,0,0,0,0,0,0,0,0,0,0,0,0,0,0,0,0,0,0,0,0,0,0,0,0,0,0,0,0,0,0,0,0,0,0,0,0,0,0,0,0,0,0,0,0,0,0,0,0,0]}",
        "executable": false,
        "lamports": 2394240,
        "owner": "stkBL96RZkjY5ine4TvPihGqW8UHJfch2cokjAPzV8i",
        "rentEpoch": 0
      },
      "pubkey": "GVtY8zRxQMsiDo4RyDYH2DVHMfnZ3vjb1HsowFvXV8Q3",
      "parsed": {
        "bump": "255",
        "pool": "HkX51yR2Xw83dnjxqdMgTp3GaAdw4FoQkwr2S3yvehdc",
        "amount": "0",
        "originalMint": "8xikjpuigCeBj8Aktu1o7wZ3Berob1L5ihhCE25HrtC1",
        "originalMintClaimed": "false",
        "lastStaker": "11111111111111111111111111111111",
        "lastStakedAt": "1673429712",
        "totalStakeSeconds": "9138611",
        "stakeMintClaimed": "false",
        "kind": "0",
        "lastUpdatedAt": "1688116433"
      }
    }
  ],
  "rewardEntries": []
}
