{
  "stakePool": {
    "account": {
      "data": "{\"type\":\"Buffer\",\"data\":[121,34,206,21,79,127,255,28,251,97,1,0,0,0,0,0,0,66,199,76,67,240,202,110,205,142,136,216,3,85,204,181,212,110,0,37,2,107,199,254,5,249,176,252,54,248,183,217,145,1,0,0,0,222,41,195,249,110,176,61,17,45,191,1,4,122,197,44,206,84,35,4,112,154,112,3,13,138,11,151,134,10,43,140,3,0,0,0,0,0,0,0,0,0,0,0,0,0,0,0,0,0,0,1,0,0,0,0,0,0,0,0,0,0,0,0,0,0,0,0,0,0,0,0,0,0,0,0,0,0,0,0,0,0,0,0,0,0,0,0,0,0,0,0,0,0,0,0,0,0,0,0,0,0,0,0,0,0,0,0,0,0,0,0,0,0,0,0,0,0,0,0,0,0,0,0,0,0,0,0,0,0,0,0,0,0,0,0,0,0,0,0,0,0,0,0,0,0,0,0,0,0,0,0,0,0,0,0,0,0,0,0,0,0,0,0,0,0,0,0,0,0,0,0,0,0,0,0,0,0,0,0,0,0,0,0,0,0,0,0,0,0,0,0,0,0,0,0,0,0,0,0,0,0,0,0,0,0,0,0,0,0,0,0,0,0,0,0,0,0,0,0,0,0,0,0,0,0,0,0,0,0,0,0,0,0,0,0,0,0,0,0,0,0,0,0,0,0,0,0,0,0,0,0,0,0,0,0,0,0,0,0,0,0,0,0,0,0,0,0,0,0,0,0,0,0,0,0,0,0,0,0,0,0,0,0,0,0,0,0,0,0,0,0,0,0,0,0,0,0,0,0,0,0,0,0,0,0,0,0,0,0,0,0,0,0,0,0,0,0,0,0,0,0,0,0,0,0,0,0,0,0,0,0,0,0,0,0,0,0,0,0,0,0,0,0,0,0,0,0,0,0,0,0,0,0,0,0,0,0,0,0,0,0,0,0,0,0,0,0,0,0,0,0,0,0,0,0,0,0,0,0,0,0,0,0,0,0,0,0,0,0,0,0,0,0,0,0,0,0,0,0,0,0,0,0,0,0,0,0,0,0,0,0,0,0]}",
      "executable": false,
      "lamports": 4134240,
      "owner": "stkBL96RZkjY5ine4TvPihGqW8UHJfch2cokjAPzV8i",
      "rentEpoch": 361
    },
    "pubkey": "25UyKBCgzaNRhZaFKKBTD1qt9RPp4VYzukTq89EnJA4D",
    "parsed": {
      "bump": "251",
      "identifier": "353",
      "authority": "5VgAkcHWcbxzM5ojbGUxqY8JZZWXsz28oiLECPEqukwA",
      "requiresCreators": "FxESuBFw2yLPvw4f7o8LpnmtqEQvujZHP96frkUK387U",
      "requiresCollections": "",
      "requiresAuthorization": "false",
      "overlayText": "",
      "imageUri": "",
      "resetOnStake": "false",
      "totalStaked": "0",
      "cooldownSeconds": "0"
    }
  },
  "rewardDistributor": {
    "timestamp": 1693962586016,
    "pubkey": "Bu9HdKSdh2fXFVUERb1Kacp9Qs39sSpdCi84APoG3t1z",
    "data": "{\"type\":\"Buffer\",\"data\":[215,10,217,199,104,194,97,227,252,16,1,163,17,82,113,247,25,15,204,151,218,39,134,154,15,202,90,5,3,66,235,234,159,134,97,178,227,110,134,196,22,2,66,199,76,67,240,202,110,205,142,136,216,3,85,204,181,212,110,0,37,2,107,199,254,5,249,176,252,54,248,183,217,145,12,163,240,206,28,35,99,212,195,25,154,219,119,251,161,155,220,155,6,176,117,5,37,233,232,29,11,178,122,237,13,87,10,0,0,0,0,0,0,0,30,0,0,0,0,0,0,0,0,0,0,0,0,0,0,0,0,0,0,0,0,0,0,0,0,0,0,0,0,0,0,0,0,1,0,0,0,0,0,0,0,0,0,0,0,0,0,0,0,0,0,0,0,0,0,0,0,0,0,0,0,0,0,0,0,0,0,0,0,0,0,0,0,0,0,0,0,0,0,0,0,0,0,0,0,0,0,0,0,0,0,0,0,0,0,0,0,0,0,0,0,0,0,0,0,0,0,0,0,0,0,0,0,0,0,0,0,0,0,0,0,0,0,0,0,0,0,0,0,0,0,0,0,0,0,0,0,0,0,0,0,0,0,0,0,0,0,0,0,0]}",
    "executable": false,
    "lamports": 2728320,
    "owner": "rwdNPNPS6zNvtF6FMvaxPRjzu2eC51mXaDT9rmWsojp",
    "rentEpoch": 361,
    "type": "rewardDistributor",
    "parsed": {
      "bump": "252",
      "stakePool": "25UyKBCgzaNRhZaFKKBTD1qt9RPp4VYzukTq89EnJA4D",
      "kind": "2",
      "authority": "5VgAkcHWcbxzM5ojbGUxqY8JZZWXsz28oiLECPEqukwA",
      "rewardMint": "rLtB6PpjGSVc8jMxFhrZaHGE5m3iixtWwyMkdVN47b4",
      "rewardAmount": "10",
      "rewardDurationSeconds": "30",
      "rewardsIssued": "0",
      "defaultMultiplier": "1",
      "multiplierDecimals": "0"
    }
  },
  "rewardDistributorTokenAccount": {
    "address": "8LLUjCHns8Adh23VQ6oJXAg5DW1r1MQXYjX5StMpGEt2",
    "mint": "rLtB6PpjGSVc8jMxFhrZaHGE5m3iixtWwyMkdVN47b4",
    "owner": "Bu9HdKSdh2fXFVUERb1Kacp9Qs39sSpdCi84APoG3t1z",
    "amount": "0",
    "delegate": null,
    "delegatedAmount": "0",
    "isInitialized": true,
    "isFrozen": false,
    "isNative": false,
    "closeAuthority": null,
    "tlvData": {
      "type": "Buffer",
      "data": "[]"
    }
  },
  "stakeEntries": [
    {
      "account": {
        "data": "{\"type\":\"Buffer\",\"data\":[187,127,9,35,155,68,86,40,255,16,1,163,17,82,113,247,25,15,204,151,218,39,134,154,15,202,90,5,3,66,235,234,159,134,97,178,227,110,134,196,22,0,0,0,0,0,0,0,0,237,0,52,67,90,223,144,7,36,14,72,213,171,101,77,133,166,174,204,24,113,246,43,217,237,245,233,143,20,143,88,80,0,0,0,0,0,0,0,0,0,0,0,0,0,0,0,0,0,0,0,0,0,0,0,0,0,0,0,0,0,0,0,0,0,192,111,53,99,0,0,0,0,9,0,0,0,0,0,0,0,0,0,0,0,0,0,0,0,0,0,0,0,0,0,0,0,0,0,0,0,0,0,0,0,0,0,0,0,0,0,0,0,0,0,0,0,0,0,0,0,0,0,0,0,0,0,0,0,0,0,0,0,0,0,0,0,0,0,0,0,0,0,0,0,0,0,0,0,0,0]}",
        "executable": false,
        "lamports": 2282880,
        "owner": "stkBL96RZkjY5ine4TvPihGqW8UHJfch2cokjAPzV8i",
        "rentEpoch": 361
      },
      "pubkey": "2tV4caryDMtHzHwBDMJpCQQQ6ZYSBUkRDDL3rvLjaJDC",
      "parsed": {
        "bump": "255",
        "pool": "25UyKBCgzaNRhZaFKKBTD1qt9RPp4VYzukTq89EnJA4D",
        "amount": "0",
        "originalMint": "Gx9ogmAadm24XmBsNCSaaVas3o7vXUt9dj5YRL9A1EhV",
        "originalMintClaimed": "false",
        "lastStaker": "11111111111111111111111111111111",
        "lastStakedAt": "1664446400",
        "totalStakeSeconds": "9",
        "stakeMintClaimed": "false",
        "kind": "0"
      }
    },
    {
      "account": {
        "data": "{\"type\":\"Buffer\",\"data\":[187,127,9,35,155,68,86,40,255,16,1,163,17,82,113,247,25,15,204,151,218,39,134,154,15,202,90,5,3,66,235,234,159,134,97,178,227,110,134,196,22,0,0,0,0,0,0,0,0,229,145,220,206,159,11,171,183,233,230,48,37,52,209,179,43,245,134,129,149,91,96,191,40,38,200,197,81,97,99,65,60,0,0,0,0,0,0,0,0,0,0,0,0,0,0,0,0,0,0,0,0,0,0,0,0,0,0,0,0,0,0,0,0,0,49,181,44,99,0,0,0,0,157,186,8,0,0,0,0,0,0,0,0,0,0,0,0,0,0,0,0,0,0,0,0,0,0,0,0,0,0,0,0,0,0,0,0,0,0,0,0,0,0,0,0,0,0,0,0,0,0,0,0,0,0,0,0,0,0,0,0,0,0,0,0,0,0,0,0,0,0,0,0,0,0,0,0,0,0,0]}",
        "executable": false,
        "lamports": 2282880,
        "owner": "stkBL96RZkjY5ine4TvPihGqW8UHJfch2cokjAPzV8i",
        "rentEpoch": 361
      },
      "pubkey": "BnV3bx1A8u1TN8WDPGvK2e4TA5rHSmMvdKwKoETTgKvs",
      "parsed": {
        "bump": "255",
        "pool": "25UyKBCgzaNRhZaFKKBTD1qt9RPp4VYzukTq89EnJA4D",
        "amount": "0",
        "originalMint": "GT9N8fLrgszPYkybUiYA2FJY9WpTP4m7nNABrciVyVXZ",
        "originalMintClaimed": "false",
        "lastStaker": "11111111111111111111111111111111",
        "lastStakedAt": "1663874353",
        "totalStakeSeconds": "572061",
        "stakeMintClaimed": "false",
        "kind": "0"
      }
    },
    {
      "account": {
        "data": "{\"type\":\"Buffer\",\"data\":[187,127,9,35,155,68,86,40,255,16,1,163,17,82,113,247,25,15,204,151,218,39,134,154,15,202,90,5,3,66,235,234,159,134,97,178,227,110,134,196,22,0,0,0,0,0,0,0,0,229,37,105,118,23,151,182,127,120,178,9,54,8,117,136,66,147,169,229,186,231,194,215,60,203,204,176,48,5,114,8,76,0,0,0,0,0,0,0,0,0,0,0,0,0,0,0,0,0,0,0,0,0,0,0,0,0,0,0,0,0,0,0,0,0,192,111,53,99,0,0,0,0,9,0,0,0,0,0,0,0,0,0,0,0,0,0,0,0,0,0,0,0,0,0,0,0,0,0,0,0,0,0,0,0,0,0,0,0,0,0,0,0,0,0,0,0,0,0,0,0,0,0,0,0,0,0,0,0,0,0,0,0,0,0,0,0,0,0,0,0,0,0,0,0,0,0,0,0,0,0]}",
        "executable": false,
        "lamports": 2282880,
        "owner": "stkBL96RZkjY5ine4TvPihGqW8UHJfch2cokjAPzV8i",
        "rentEpoch": 361
      },
      "pubkey": "EnTza3fbzXCNiDu8xFhazdQH8bWN1Dms5nugEMA92CvP",
      "parsed": {
        "bump": "255",
        "pool": "25UyKBCgzaNRhZaFKKBTD1qt9RPp4VYzukTq89EnJA4D",
        "amount": "0",
        "originalMint": "GRVT7BQnYRkJECHYquc5eXCabHrM7WyD4gCsCZKN4yDm",
        "originalMintClaimed": "false",
        "lastStaker": "11111111111111111111111111111111",
        "lastStakedAt": "1664446400",
        "totalStakeSeconds": "9",
        "stakeMintClaimed": "false",
        "kind": "0"
      }
    }
  ],
  "rewardEntries": [
    {
      "account": {
        "data": "{\"type\":\"Buffer\",\"data\":[208,191,173,14,213,84,179,162,252,204,205,150,73,157,59,210,142,75,214,4,195,57,93,170,127,244,179,240,27,252,118,119,108,81,49,7,175,158,71,234,108,161,240,112,235,64,84,180,210,155,21,38,255,128,123,119,4,37,148,144,121,141,99,198,143,81,0,247,209,220,178,182,101,0,0,0,0,0,0,0,0,0,0,0,0,0,0,0,0,1,0,0,0,0,0,0,0,0,0,0,0,0,0,0,0,0,0,0,0,0,0,0,0,0,0,0,0,0,0,0,0,0,0,0,0,0,0,0,0,0,0,0,0,0,0,0,0,0,0,0,0,0,0,0,0,0,0,0,0,0,0,0,0,0,0,0,0,0,0,0,0,0,0,0,0,0,0,0]}",
        "executable": false,
        "lamports": 2060160,
        "owner": "rwdNPNPS6zNvtF6FMvaxPRjzu2eC51mXaDT9rmWsojp",
        "rentEpoch": 361
      },
      "pubkey": "3qxb4iJjTtW58ebH7VvntWgwSB2BhAc9xT9VBqsAUSSX",
      "parsed": {
        "bump": "252",
        "stakeEntry": "EnTza3fbzXCNiDu8xFhazdQH8bWN1Dms5nugEMA92CvP",
        "rewardDistributor": "Bu9HdKSdh2fXFVUERb1Kacp9Qs39sSpdCi84APoG3t1z",
        "rewardSecondsReceived": "0",
        "multiplier": "1"
      }
    },
    {
      "account": {
        "data": "{\"type\":\"Buffer\",\"data\":[208,191,173,14,213,84,179,162,255,28,12,9,208,85,117,39,34,150,35,223,78,130,139,172,233,210,99,113,117,161,28,165,29,171,94,178,209,56,103,14,143,161,240,112,235,64,84,180,210,155,21,38,255,128,123,119,4,37,148,144,121,141,99,198,143,81,0,247,209,220,178,182,101,0,0,0,0,0,0,0,0,0,0,0,0,0,0,0,0,1,0,0,0,0,0,0,0,0,0,0,0,0,0,0,0,0,0,0,0,0,0,0,0,0,0,0,0,0,0,0,0,0,0,0,0,0,0,0,0,0,0,0,0,0,0,0,0,0,0,0,0,0,0,0,0,0,0,0,0,0,0,0,0,0,0,0,0,0,0,0,0,0,0,0,0,0,0,0]}",
        "executable": false,
        "lamports": 2060160,
        "owner": "rwdNPNPS6zNvtF6FMvaxPRjzu2eC51mXaDT9rmWsojp",
        "rentEpoch": 361
      },
      "pubkey": "4MFLhpNsWMLjbLU2ePPxe6xLtp6t3WueyLKVUZkBKdiq",
      "parsed": {
        "bump": "255",
        "stakeEntry": "2tV4caryDMtHzHwBDMJpCQQQ6ZYSBUkRDDL3rvLjaJDC",
        "rewardDistributor": "Bu9HdKSdh2fXFVUERb1Kacp9Qs39sSpdCi84APoG3t1z",
        "rewardSecondsReceived": "0",
        "multiplier": "1"
      }
    },
    {
      "account": {
        "data": "{\"type\":\"Buffer\",\"data\":[208,191,173,14,213,84,179,162,254,160,59,183,82,242,24,136,96,127,151,237,189,219,182,111,215,81,63,150,114,183,144,230,73,119,203,159,154,53,243,52,244,161,240,112,235,64,84,180,210,155,21,38,255,128,123,119,4,37,148,144,121,141,99,198,143,81,0,247,209,220,178,182,101,0,0,0,0,0,0,0,0,0,0,0,0,0,0,0,0,1,0,0,0,0,0,0,0,0,0,0,0,0,0,0,0,0,0,0,0,0,0,0,0,0,0,0,0,0,0,0,0,0,0,0,0,0,0,0,0,0,0,0,0,0,0,0,0,0,0,0,0,0,0,0,0,0,0,0,0,0,0,0,0,0,0,0,0,0,0,0,0,0,0,0,0,0,0,0]}",
        "executable": false,
        "lamports": 2060160,
        "owner": "rwdNPNPS6zNvtF6FMvaxPRjzu2eC51mXaDT9rmWsojp",
        "rentEpoch": 361
      },
      "pubkey": "6uSQztftncus7NWxc5ameeANKaKWyATXTB4zBiL67ka6",
      "parsed": {
        "bump": "254",
        "stakeEntry": "BnV3bx1A8u1TN8WDPGvK2e4TA5rHSmMvdKwKoETTgKvs",
        "rewardDistributor": "Bu9HdKSdh2fXFVUERb1Kacp9Qs39sSpdCi84APoG3t1z",
        "rewardSecondsReceived": "0",
        "multiplier": "1"
      }
    }
  ]
}
