{
  "stakePool": {
    "account": {
      "data": "{\"type\":\"Buffer\",\"data\":[121,34,206,21,79,127,255,28,255,251,0,0,0,0,0,0,0,198,164,197,206,186,244,34,86,89,253,216,174,140,154,149,118,22,93,160,135,248,111,131,230,212,112,215,15,226,53,5,187,1,0,0,0,40,207,157,129,233,112,106,106,40,160,89,243,1,64,46,151,95,204,101,222,86,46,175,58,86,91,178,93,129,140,244,187,0,0,0,0,1,6,0,0,0,83,84,65,75,69,68,0,0,0,0,0,0,0,0,0,1,5,0,0,0,1,128,58,9,0,1,128,123,175,99,0,0,0,0,0,0,0,0,0,0,0,0,0,0,0,0,0,0,0,0,0,0,0,0,0,0,0,0,0,0,0,0,0,0,0,0,0,0,0,0,0,0,0,0,0,0,0,0,0,0,0,0,0,0,0,0,0,0,0,0,0,0,0,0,0,0,0,0,0,0,0,0,0,0,0,0,0,0,0,0,0,0,0,0,0,0,0,0,0,0,0,0,0,0,0,0,0,0,0,0,0,0,0,0,0,0,0,0,0,0,0,0,0,0,0,0,0,0,0,0,0,0,0,0,0,0,0,0,0,0,0,0,0,0,0,0,0,0,0,0,0,0,0,0,0,0,0,0,0,0,0,0,0,0,0,0,0,0,0,0,0,0,0,0,0,0,0,0,0,0,0,0,0,0,0,0,0,0,0,0,0,0,0,0,0,0,0,0,0,0,0,0,0,0,0,0,0,0,0,0,0,0,0,0,0,0,0,0,0,0,0,0,0,0,0,0,0,0,0,0,0,0,0,0,0,0,0,0,0,0,0,0,0,0,0,0,0,0,0,0,0,0,0,0,0,0,0,0,0,0,0,0,0,0,0,0,0,0,0,0,0,0,0,0,0,0,0,0,0,0,0,0,0,0,0,0,0,0,0,0,0,0,0,0,0,0,0,0,0,0,0,0,0,0,0,0,0,0,0,0,0,0,0,0,0,0,0,0,0,0,0,0,0,0,0,0,0,0,0,0,0,0,0,0,0,0,0,0,0,0,0,0,0,0,0,0,0,0,0,0,0,0]}",
      "executable": false,
      "lamports": 4134240,
      "owner": "stkBL96RZkjY5ine4TvPihGqW8UHJfch2cokjAPzV8i",
      "rentEpoch": 361
    },
    "pubkey": "AEo6u5k2FPHGv36eURQtndbabaZ1gHHGbMUx4T2veb3a",
    "parsed": {
      "bump": "255",
      "identifier": "251",
      "authority": "ENRT6eftXTfLHFwRGmiJxFkfqDzAyCYRvhNgXKoX5VTg",
      "requiresCreators": "3kJvb1NRjNEuXq1ysCLCwoe9F7qsVKVQr1J1XcGoyCVQ",
      "requiresCollections": "",
      "requiresAuthorization": "true",
      "overlayText": "STAKED",
      "imageUri": "",
      "resetOnStake": "false",
      "totalStaked": "0",
      "cooldownSeconds": "5",
      "minStakeSeconds": "604800",
      "endDate": "1672444800"
    }
  },
  "rewardDistributor": {
    "timestamp": 1693962586051,
    "pubkey": "9btJkUBzHCBQPEaa5PbRWxgpeu8sc9YyNzVwgPqMSRjE",
    "data": "{\"type\":\"Buffer\",\"data\":[215,10,217,199,104,194,97,227,253,137,65,220,54,35,39,56,84,204,152,130,57,209,188,72,85,120,153,69,114,248,14,148,156,74,116,44,11,151,135,216,21,2,198,164,197,206,186,244,34,86,89,253,216,174,140,154,149,118,22,93,160,135,248,111,131,230,212,112,215,15,226,53,5,187,50,69,30,74,228,240,19,49,121,59,91,160,83,69,54,21,252,86,175,42,84,232,19,231,234,138,163,168,49,205,195,245,0,225,245,5,0,0,0,0,192,33,0,0,0,0,0,0,0,0,0,0,0,0,0,0,0,0,0,0,0,0,0,0,0,0,0,0,0,0,0,0,0,1,0,0,0,0,0,0,0,0,0,0,0,0,0,0,0,0,0,0,0,0,0,0,0,0,0,0,0,0,0,0,0,0,0,0,0,0,0,0,0,0,0,0,0,0,0,0,0,0,0,0,0,0,0,0,0,0,0,0,0,0,0,0,0,0,0,0,0,0,0,0,0,0,0,0,0,0,0,0,0,0,0,0,0,0,0,0,0,0,0,0,0,0]}",
    "executable": false,
    "lamports": 2561280,
    "owner": "rwdNPNPS6zNvtF6FMvaxPRjzu2eC51mXaDT9rmWsojp",
    "rentEpoch": 361,
    "type": "rewardDistributor",
    "parsed": {
      "bump": "253",
      "stakePool": "AEo6u5k2FPHGv36eURQtndbabaZ1gHHGbMUx4T2veb3a",
      "kind": "2",
      "authority": "ENRT6eftXTfLHFwRGmiJxFkfqDzAyCYRvhNgXKoX5VTg",
      "rewardMint": "4PEWnP1rWDxEh6Km5FugUmQ6weSX4UD8vvWjp5tUTHt8",
      "rewardAmount": "100000000",
      "rewardDurationSeconds": "8640",
      "rewardsIssued": "0",
      "defaultMultiplier": "1",
      "multiplierDecimals": "0"
    }
  },
  "rewardDistributorTokenAccount": {
    "address": "HzijS59Aj6jd86zghsqe4wxBsA72Hwn5CcozEi8aCgU2",
    "mint": "4PEWnP1rWDxEh6Km5FugUmQ6weSX4UD8vvWjp5tUTHt8",
    "owner": "9btJkUBzHCBQPEaa5PbRWxgpeu8sc9YyNzVwgPqMSRjE",
    "amount": "0",
    "delegate": null,
    "delegatedAmount": "0",
    "isInitialized": true,
    "isFrozen": false,
    "isNative": false,
    "closeAuthority": null,
    "tlvData": {
      "type": "Buffer",
      "data": "[]"
    }
  },
  "stakeEntries": [
    {
      "account": {
        "data": "{\"type\":\"Buffer\",\"data\":[187,127,9,35,155,68,86,40,250,137,65,220,54,35,39,56,84,204,152,130,57,209,188,72,85,120,153,69,114,248,14,148,156,74,116,44,11,151,135,216,21,0,0,0,0,0,0,0,0,176,42,246,201,217,148,172,92,97,170,248,105,180,169,77,226,236,131,46,3,39,3,100,37,22,179,247,119,110,192,71,173,0,0,0,0,0,0,0,0,0,0,0,0,0,0,0,0,0,0,0,0,0,0,0,0,0,0,0,0,0,0,0,0,0,172,183,0,99,0,0,0,0,66,30,235,1,0,0,0,0,0,0,0,0,0,0,0,0,0,0,0,0,1,192,213,235,100,0,0,0,0,0,0,0,0,0,0,0,0,0,0,0,0,0,0,0,0,0,0,0,0,0,0,0,0,0,0,0,0,0,0,0,0,0,0,0,0,0,0,0,0,0,0,0,0,0,0,0,0,0]}",
        "executable": false,
        "lamports": 2282880,
        "owner": "stkBL96RZkjY5ine4TvPihGqW8UHJfch2cokjAPzV8i",
        "rentEpoch": 361
      },
      "pubkey": "DAW5j2XtHvuJWJ9uGHGKv8uj1vGWCVHDf5itE3rrmiRD",
      "parsed": {
        "bump": "250",
        "pool": "AEo6u5k2FPHGv36eURQtndbabaZ1gHHGbMUx4T2veb3a",
        "amount": "0",
        "originalMint": "Crgke5S9gg2kpfQY6ZjwE8uvVoyGFkq6gFEGZUrTMwTJ",
        "originalMintClaimed": "false",
        "lastStaker": "11111111111111111111111111111111",
        "lastStakedAt": "1660991404",
        "totalStakeSeconds": "32185922",
        "stakeMintClaimed": "false",
        "kind": "0",
        "lastUpdatedAt": "1693177280"
      }
    }
  ],
  "rewardEntries": [
    {
      "account": {
        "data": "{\"type\":\"Buffer\",\"data\":[208,191,173,14,213,84,179,162,255,180,187,90,88,43,146,45,169,243,179,88,173,249,156,194,179,3,107,117,16,203,0,32,15,229,239,220,27,132,96,212,208,127,205,65,60,87,213,79,67,22,71,121,111,39,13,246,242,79,69,127,11,247,237,170,237,186,194,235,252,88,133,3,25,0,0,0,0,0,0,0,0,0,0,0,0,0,0,0,0,1,0,0,0,0,0,0,0,0,0,0,0,0,0,0,0,0,0,0,0,0,0,0,0,0,0,0,0,0,0,0,0,0,0,0,0,0,0,0,0,0,0,0,0,0,0,0,0,0,0,0,0,0,0,0,0,0,0,0,0,0,0,0,0,0,0,0,0,0,0,0,0,0,0,0,0,0,0,0]}",
        "executable": false,
        "lamports": 2060160,
        "owner": "rwdNPNPS6zNvtF6FMvaxPRjzu2eC51mXaDT9rmWsojp",
        "rentEpoch": 361
      },
      "pubkey": "9TjpJp5yAHvnkj8hzaW2FwtqLEsxczvhUgBPeJ6J4Hem",
      "parsed": {
        "bump": "255",
        "stakeEntry": "DAW5j2XtHvuJWJ9uGHGKv8uj1vGWCVHDf5itE3rrmiRD",
        "rewardDistributor": "9btJkUBzHCBQPEaa5PbRWxgpeu8sc9YyNzVwgPqMSRjE",
        "rewardSecondsReceived": "0",
        "multiplier": "1"
      }
    }
  ]
}
