{
  "stakePool": {
    "account": {
      "data": "{\"type\":\"Buffer\",\"data\":[121,34,206,21,79,127,255,28,255,89,3,0,0,0,0,0,0,114,137,124,246,133,218,8,229,98,194,186,183,60,173,37,45,210,81,152,122,217,18,87,131,159,27,145,242,181,66,43,213,1,0,0,0,182,68,4,58,105,129,136,141,149,42,56,245,169,78,105,170,60,111,209,56,116,150,212,223,216,8,55,48,158,71,140,156,0,0,0,0,0,6,0,0,0,83,84,65,75,69,68,0,0,0,0,0,6,0,0,0,1,0,0,0,0,1,0,0,0,0,1,128,247,140,100,0,0,0,0,1,0,0,0,0,0,0,0,0,0,0,0,0,0,0,0,0,0,0,0,0,0,0,0,0,0,0,0,0,0,0,0,0,0,0,0,0,0,0,0,0,0,0,0,0,0,0,0,0,0,0,0,0,0,0,0,0,0,0,0,0,0,0,0,0,0,0,0,0,0,0,0,0,0,0,0,0,0,0,0,0,0,0,0,0,0,0,0,0,0,0,0,0,0,0,0,0,0,0,0,0,0,0,0,0,0,0,0,0,0,0,0,0,0,0,0,0,0,0,0,0,0,0,0,0,0,0,0,0,0,0,0,0,0,0,0,0,0,0,0,0,0,0,0,0,0,0,0,0,0,0,0,0,0,0,0,0,0,0,0,0,0,0,0,0,0,0,0,0,0,0,0,0,0,0,0,0,0,0,0,0,0,0,0,0,0,0,0,0,0,0,0,0,0,0,0,0,0,0,0,0,0,0,0,0,0,0,0,0,0,0,0,0,0,0,0,0,0,0,0,0,0,0,0,0,0,0,0,0,0,0,0,0,0,0,0,0,0,0,0,0,0,0,0,0,0,0,0,0,0,0,0,0,0,0,0,0,0,0,0,0,0,0,0,0,0,0,0,0,0,0,0,0,0,0,0,0,0,0,0,0,0,0,0,0,0,0,0,0,0,0,0,0,0,0,0,0,0,0,0,0,0,0,0,0,0,0,0,0,0,0,0,0,0,0,0,0,0,0,0,0,0,0,0,0,0,0,0,0,0,0,0,0,0,0,0,0,0]}",
      "executable": false,
      "lamports": 4134240,
      "owner": "stkBL96RZkjY5ine4TvPihGqW8UHJfch2cokjAPzV8i",
      "rentEpoch": 0
    },
    "pubkey": "FgHa3zSwqVjDWRg49DaCt1pjXkPTJc4mrF63j2HnA8i5",
    "parsed": {
      "bump": "255",
      "identifier": "857",
      "authority": "8i75DjMtuoeCSvXMCBWSTfDBBQmJTdWQTdSPqKRqtvqA",
      "requiresCreators": "DGVMbhvmJpmBE9dsht4Yf9BP5qP1ZoJo1oC55zQn3KUw",
      "requiresCollections": "",
      "requiresAuthorization": "false",
      "overlayText": "STAKED",
      "imageUri": "",
      "resetOnStake": "false",
      "totalStaked": "6",
      "cooldownSeconds": "0",
      "minStakeSeconds": "0",
      "endDate": "1686960000",
      "doubleOrResetEnabled": "false"
    }
  },
  "rewardDistributor": {
    "timestamp": 1693168060005,
    "pubkey": "2scgxUvUSok1sTBap3aHzjKJANK8zqzqpuGucsKHtiqr",
    "data": "{\"type\":\"Buffer\",\"data\":[215,10,217,199,104,194,97,227,253,218,20,1,13,208,165,222,84,191,198,180,66,212,151,104,206,30,196,246,219,175,79,120,238,18,33,97,104,249,7,57,194,2,114,137,124,246,133,218,8,229,98,194,186,183,60,173,37,45,210,81,152,122,217,18,87,131,159,27,145,242,181,66,43,213,136,81,253,81,25,113,158,205,88,121,230,137,238,86,250,23,70,44,149,141,35,47,255,212,156,216,157,67,233,80,255,244,0,202,154,59,0,0,0,0,128,81,1,0,0,0,0,0,0,0,0,0,0,0,0,0,0,152,5,57,51,0,0,0,0,0,0,0,0,0,0,0,0,1,0,0,0,0,0,0,0,0,0,0,0,0,0,0,0,0,0,0,0,0,0,0,0,0,0,0,0,0,0,0,0,0,0,0,0,0,0,0,0,0,0,0,0,0,0,0,0,0,0,0,0,0,0,0,0,0,0,0,0,0,0,0,0,0,0,0,0,0,0,0,0,0,0,0,0,0,0,0,0,0,0,0,0,0,0,0,0,0,0,0,0,0,0,0,0,0,0,0,0,0,0,0,0,0,0,0,0,0,0,0,0,0,0,0,0,0]}",
    "executable": false,
    "lamports": 2728320,
    "owner": "rwdNPNPS6zNvtF6FMvaxPRjzu2eC51mXaDT9rmWsojp",
    "rentEpoch": 0,
    "type": "rewardDistributor",
    "parsed": {
      "bump": "253",
      "stakePool": "FgHa3zSwqVjDWRg49DaCt1pjXkPTJc4mrF63j2HnA8i5",
      "kind": "2",
      "authority": "8i75DjMtuoeCSvXMCBWSTfDBBQmJTdWQTdSPqKRqtvqA",
      "rewardMint": "AB8xcYVLAMJRyyBExiaXG4VaaKgfcFZU6bpRENWrPFtF",
      "rewardAmount": "1000000000",
      "rewardDurationSeconds": "86400",
      "rewardsIssued": "220000000000",
      "defaultMultiplier": "1",
      "multiplierDecimals": "0"
    }
  },
  "rewardDistributorTokenAccount": {
    "address": "5Mea49X91GDfiEmoh89BampDKMCrTvmEJoh7EBvmFZKa",
    "mint": "AB8xcYVLAMJRyyBExiaXG4VaaKgfcFZU6bpRENWrPFtF",
    "owner": "2scgxUvUSok1sTBap3aHzjKJANK8zqzqpuGucsKHtiqr",
    "amount": "1780000000000",
    "delegate": null,
    "delegatedAmount": "0",
    "isInitialized": true,
    "isFrozen": false,
    "isNative": false,
    "closeAuthority": null,
    "tlvData": {
      "type": "Buffer",
      "data": "[]"
    }
  },
  "stakeEntries": [
    {
      "account": {
        "data": "{\"type\":\"Buffer\",\"data\":[187,127,9,35,155,68,86,40,255,218,20,1,13,208,165,222,84,191,198,180,66,212,151,104,206,30,196,246,219,175,79,120,238,18,33,97,104,249,7,57,194,1,0,0,0,0,0,0,0,132,180,221,186,60,114,8,0,63,145,70,110,42,17,48,152,215,185,68,10,116,55,194,28,210,163,133,248,44,215,182,29,1,205,17,194,114,121,76,143,96,202,89,227,108,180,236,52,15,113,6,132,72,148,21,115,205,93,216,40,60,52,152,194,187,31,30,200,99,0,0,0,0,168,114,34,1,0,0,0,0,0,0,0,0,0,0,0,0,0,1,0,0,1,199,144,234,100,0,0,0,0,0,0,0,0,0,0,0,0,0,0,0,0,0,0,0,0,0,0,0,0,0,0,0,0,0,0,0,0,0,0,0,0,0,0,0,0,0,0,0,0,0,0,0,0,0,0,0,0,0,0,0,0,0,0,0,0,0,0,0,0,0,0,0,0,0]}",
        "executable": false,
        "lamports": 2394240,
        "owner": "stkBL96RZkjY5ine4TvPihGqW8UHJfch2cokjAPzV8i",
        "rentEpoch": 0
      },
      "pubkey": "4hBSHssU6G7dokhuSLVMhuvfwcLHe3ExpuxYRqFC3omE",
      "parsed": {
        "bump": "255",
        "pool": "FgHa3zSwqVjDWRg49DaCt1pjXkPTJc4mrF63j2HnA8i5",
        "amount": "1",
        "originalMint": "9w2mxAomt9qks6H26HaRiv7cHrucXrKpWiZ8SANkzZPi",
        "originalMintClaimed": "true",
        "lastStaker": "EoWHWgWj65GNBx2RUzx2Tk4wvZwYbxRqZ38f8t1AJB4n",
        "lastStakedAt": "1674059295",
        "totalStakeSeconds": "19034792",
        "stakeMintClaimed": "false",
        "kind": "1",
        "lastUpdatedAt": "1693094087"
      }
    },
    {
      "account": {
        "data": "{\"type\":\"Buffer\",\"data\":[187,127,9,35,155,68,86,40,253,218,20,1,13,208,165,222,84,191,198,180,66,212,151,104,206,30,196,246,219,175,79,120,238,18,33,97,104,249,7,57,194,1,0,0,0,0,0,0,0,110,135,228,123,162,245,190,254,250,138,103,244,129,162,218,202,178,152,26,103,236,8,8,160,6,219,170,98,178,189,5,124,1,114,137,124,246,133,218,8,229,98,194,186,183,60,173,37,45,210,81,152,122,217,18,87,131,159,27,145,242,181,66,43,213,145,252,198,99,0,0,0,0,0,0,0,0,0,0,0,0,0,0,0,0,0,0,0,0,0,0,0,0,1,145,252,198,99,0,0,0,0,0,0,0,0,0,0,0,0,0,0,0,0,0,0,0,0,0,0,0,0,0,0,0,0,0,0,0,0,0,0,0,0,0,0,0,0,0,0,0,0,0,0,0,0,0,0,0,0,0,0,0,0,0,0,0,0,0,0,0,0,0,0,0,0,0]}",
        "executable": false,
        "lamports": 2394240,
        "owner": "stkBL96RZkjY5ine4TvPihGqW8UHJfch2cokjAPzV8i",
        "rentEpoch": 0
      },
      "pubkey": "An5uxNyr3invHNiDWanSX6Ww7KCeHE8pNC19go4vBGSV",
      "parsed": {
        "bump": "253",
        "pool": "FgHa3zSwqVjDWRg49DaCt1pjXkPTJc4mrF63j2HnA8i5",
        "amount": "1",
        "originalMint": "8SU2nYWur3KqV8smcpJ9UkCESj59U2RExWJUtzBkan2P",
        "originalMintClaimed": "true",
        "lastStaker": "8i75DjMtuoeCSvXMCBWSTfDBBQmJTdWQTdSPqKRqtvqA",
        "lastStakedAt": "1673985169",
        "totalStakeSeconds": "0",
        "stakeMintClaimed": "false",
        "kind": "0",
        "lastUpdatedAt": "1673985169"
      }
    },
    {
      "account": {
        "data": "{\"type\":\"Buffer\",\"data\":[187,127,9,35,155,68,86,40,252,218,20,1,13,208,165,222,84,191,198,180,66,212,151,104,206,30,196,246,219,175,79,120,238,18,33,97,104,249,7,57,194,1,0,0,0,0,0,0,0,43,174,190,232,140,155,204,59,177,162,50,208,100,200,15,211,177,215,10,147,171,127,100,157,55,137,181,182,247,241,11,195,1,21,248,98,215,113,93,63,12,128,47,133,254,20,106,199,26,243,49,27,113,235,252,128,157,76,162,123,79,2,138,54,231,230,191,200,99,0,0,0,0,0,0,0,0,0,0,0,0,0,0,0,0,0,0,0,0,0,0,0,0,1,230,191,200,99,0,0,0,0,0,0,0,0,0,0,0,0,0,0,0,0,0,0,0,0,0,0,0,0,0,0,0,0,0,0,0,0,0,0,0,0,0,0,0,0,0,0,0,0,0,0,0,0,0,0,0,0,0,0,0,0,0,0,0,0,0,0,0,0,0,0,0,0,0]}",
        "executable": false,
        "lamports": 2394240,
        "owner": "stkBL96RZkjY5ine4TvPihGqW8UHJfch2cokjAPzV8i",
        "rentEpoch": 0
      },
      "pubkey": "BypGeA7GJXxaorEv7fbnZQA4KcLeCYjU3TYgCAAiKeyL",
      "parsed": {
        "bump": "252",
        "pool": "FgHa3zSwqVjDWRg49DaCt1pjXkPTJc4mrF63j2HnA8i5",
        "amount": "1",
        "originalMint": "3wX5U6DoJcZXFhQZzmRzTDatsJePvRaB8isS93YiiqPp",
        "originalMintClaimed": "true",
        "lastStaker": "2UmEfVGfKd8ps2qe9jY9RawwXeHqNP8CHxSQje8K5frN",
        "lastStakedAt": "1674100710",
        "totalStakeSeconds": "0",
        "stakeMintClaimed": "false",
        "kind": "0",
        "lastUpdatedAt": "1674100710"
      }
    },
    {
      "account": {
        "data": "{\"type\":\"Buffer\",\"data\":[187,127,9,35,155,68,86,40,255,218,20,1,13,208,165,222,84,191,198,180,66,212,151,104,206,30,196,246,219,175,79,120,238,18,33,97,104,249,7,57,194,1,0,0,0,0,0,0,0,30,89,66,56,103,51,128,8,5,83,200,27,68,25,163,11,176,189,84,193,52,173,77,222,172,133,174,175,163,204,195,212,1,161,224,88,177,104,27,203,210,65,225,56,240,82,37,159,140,241,165,188,10,30,23,8,219,86,244,55,23,99,53,38,246,110,248,200,99,0,0,0,0,0,0,0,0,0,0,0,0,0,0,0,0,0,0,0,0,0,0,0,0,1,110,248,200,99,0,0,0,0,0,0,0,0,0,0,0,0,0,0,0,0,0,0,0,0,0,0,0,0,0,0,0,0,0,0,0,0,0,0,0,0,0,0,0,0,0,0,0,0,0,0,0,0,0,0,0,0,0,0,0,0,0,0,0,0,0,0,0,0,0,0,0,0,0]}",
        "executable": false,
        "lamports": 2394240,
        "owner": "stkBL96RZkjY5ine4TvPihGqW8UHJfch2cokjAPzV8i",
        "rentEpoch": 0
      },
      "pubkey": "CV4dfGAaeTfR986p3s2Z51Bc3Ujurk1Q1nBEGk3FzoRQ",
      "parsed": {
        "bump": "255",
        "pool": "FgHa3zSwqVjDWRg49DaCt1pjXkPTJc4mrF63j2HnA8i5",
        "amount": "1",
        "originalMint": "33UAxndQfmsZQTD6pX43Yocw3555qyTR3FdX67DGDNVy",
        "originalMintClaimed": "true",
        "lastStaker": "Btu43Z9dM6QEch8bDKDiZSPvRMGmsQNr3cah3f2fbq2m",
        "lastStakedAt": "1674115182",
        "totalStakeSeconds": "0",
        "stakeMintClaimed": "false",
        "kind": "0",
        "lastUpdatedAt": "1674115182"
      }
    },
    {
      "account": {
        "data": "{\"type\":\"Buffer\",\"data\":[187,127,9,35,155,68,86,40,255,218,20,1,13,208,165,222,84,191,198,180,66,212,151,104,206,30,196,246,219,175,79,120,238,18,33,97,104,249,7,57,194,1,0,0,0,0,0,0,0,46,224,36,9,230,84,40,219,169,145,32,57,206,53,7,229,20,132,83,189,36,151,84,107,15,98,186,128,32,216,116,176,1,62,104,170,33,195,107,164,224,239,143,152,249,31,144,172,20,219,178,49,102,216,7,171,127,217,251,22,119,23,64,97,35,250,16,199,99,0,0,0,0,0,0,0,0,0,0,0,0,0,0,0,0,0,0,0,0,0,0,0,0,1,250,16,199,99,0,0,0,0,0,0,0,0,0,0,0,0,0,0,0,0,0,0,0,0,0,0,0,0,0,0,0,0,0,0,0,0,0,0,0,0,0,0,0,0,0,0,0,0,0,0,0,0,0,0,0,0,0,0,0,0,0,0,0,0,0,0,0,0,0,0,0,0,0]}",
        "executable": false,
        "lamports": 2394240,
        "owner": "stkBL96RZkjY5ine4TvPihGqW8UHJfch2cokjAPzV8i",
        "rentEpoch": 0
      },
      "pubkey": "CV5j1n7fdsPcatUGkLUd47iSVg68XBzqCeenXy2EGHZt",
      "parsed": {
        "bump": "255",
        "pool": "FgHa3zSwqVjDWRg49DaCt1pjXkPTJc4mrF63j2HnA8i5",
        "amount": "1",
        "originalMint": "49yz9foaPoDnyXDMDnC7C8JA6SwRsRkS7bKF5mWTNAsH",
        "originalMintClaimed": "true",
        "lastStaker": "5CcquLZybaT8weVRqMmR2FZbzAF2T4qdVzRoT7T2mbtW",
        "lastStakedAt": "1673990394",
        "totalStakeSeconds": "0",
        "stakeMintClaimed": "false",
        "kind": "0",
        "lastUpdatedAt": "1673990394"
      }
    },
    {
      "account": {
        "data": "{\"type\":\"Buffer\",\"data\":[187,127,9,35,155,68,86,40,255,218,20,1,13,208,165,222,84,191,198,180,66,212,151,104,206,30,196,246,219,175,79,120,238,18,33,97,104,249,7,57,194,1,0,0,0,0,0,0,0,243,207,33,133,54,96,82,128,254,14,202,72,228,89,61,221,145,38,124,90,222,215,39,255,46,57,199,162,197,68,81,209,1,114,137,124,246,133,218,8,229,98,194,186,183,60,173,37,45,210,81,152,122,217,18,87,131,159,27,145,242,181,66,43,213,145,252,198,99,0,0,0,0,0,0,0,0,0,0,0,0,0,0,0,0,0,0,0,0,0,0,0,0,1,145,252,198,99,0,0,0,0,0,0,0,0,0,0,0,0,0,0,0,0,0,0,0,0,0,0,0,0,0,0,0,0,0,0,0,0,0,0,0,0,0,0,0,0,0,0,0,0,0,0,0,0,0,0,0,0,0,0,0,0,0,0,0,0,0,0,0,0,0,0,0,0,0]}",
        "executable": false,
        "lamports": 2394240,
        "owner": "stkBL96RZkjY5ine4TvPihGqW8UHJfch2cokjAPzV8i",
        "rentEpoch": 0
      },
      "pubkey": "uQsWQmjav1DDUpTUg71VJm8Q7JAJyS6nMdfkms3tgT5",
      "parsed": {
        "bump": "255",
        "pool": "FgHa3zSwqVjDWRg49DaCt1pjXkPTJc4mrF63j2HnA8i5",
        "amount": "1",
        "originalMint": "HQjFycZ7GNot3dChWHq2Q9nprZtqjd6Lm6gPRCdNjhvG",
        "originalMintClaimed": "true",
        "lastStaker": "8i75DjMtuoeCSvXMCBWSTfDBBQmJTdWQTdSPqKRqtvqA",
        "lastStakedAt": "1673985169",
        "totalStakeSeconds": "0",
        "stakeMintClaimed": "false",
        "kind": "0",
        "lastUpdatedAt": "1673985169"
      }
    }
  ],
  "rewardEntries": [
    {
      "account": {
        "data": "{\"type\":\"Buffer\",\"data\":[208,191,173,14,213,84,179,162,253,54,222,23,221,119,64,62,67,139,66,172,72,151,185,178,6,102,52,24,174,19,242,86,131,21,139,232,218,155,253,206,61,27,211,20,185,124,208,74,49,69,230,39,119,104,63,249,129,72,188,190,74,51,162,36,65,125,119,67,21,70,111,252,13,0,10,34,1,0,0,0,0,0,0,0,0,0,0,0,0,1,0,0,0,0,0,0,0,0,0,0,0,0,0,0,0,0,0,0,0,0,0,0,0,0,0,0,0,0,0,0,0,0,0,0,0,0,0,0,0,0,0,0,0,0,0,0,0,0,0,0,0,0,0,0,0,0,0,0,0,0,0,0,0,0,0,0,0,0,0,0,0,0,0,0,0,0,0,0]}",
        "executable": false,
        "lamports": 2060160,
        "owner": "rwdNPNPS6zNvtF6FMvaxPRjzu2eC51mXaDT9rmWsojp",
        "rentEpoch": 0
      },
      "pubkey": "GarTfk7QfodgE6yCN42CU3Y7b7ogvyC49WVNWzubjjDR",
      "parsed": {
        "bump": "253",
        "stakeEntry": "4hBSHssU6G7dokhuSLVMhuvfwcLHe3ExpuxYRqFC3omE",
        "rewardDistributor": "2scgxUvUSok1sTBap3aHzjKJANK8zqzqpuGucsKHtiqr",
        "rewardSecondsReceived": "19008000",
        "multiplier": "1"
      }
    }
  ]
}
