{
  "stakePool": {
    "account": {
      "data": "{\"type\":\"Buffer\",\"data\":[121,34,206,21,79,127,255,28,255,20,0,0,0,0,0,0,0,189,237,130,185,121,84,62,179,99,176,59,161,10,60,125,8,163,222,87,100,179,49,135,250,136,175,196,21,225,157,77,127,0,0,0,0,0,0,0,0,0,6,0,0,0,83,84,65,75,69,68,0,0,0,0,0,0,0,0,0,0,0,0,0,0,0,0,0,0,0,0,0,0,0,0,0,0,0,0,0,0,0,0,0,0,0,0,0,0,0,0,0,0,0,0,0,0,0,0,0,0,0,0,0,0,0,0,0,0,0,0,0,0,0,0,0,0,0,0,0,0,0,0,0,0,0,0,0,0,0,0,0,0,0,0,0,0,0,0,0,0,0,0,0,0,0,0,0,0,0,0,0,0,0,0,0,0,0,0,0,0,0,0,0,0,0,0,0,0,0,0,0,0,0,0,0,0,0,0,0,0,0,0,0,0,0,0,0,0,0,0,0,0,0,0,0,0,0,0,0,0,0,0,0,0,0,0,0,0,0,0,0,0,0,0,0,0,0,0,0,0,0,0,0,0,0,0,0,0,0,0,0,0,0,0,0,0,0,0,0,0,0,0,0,0,0,0,0,0,0,0,0,0,0,0,0,0,0,0,0,0,0,0,0,0,0,0,0,0,0,0,0,0,0,0,0,0,0,0,0,0,0,0,0,0,0,0,0,0,0,0,0,0,0,0,0,0,0,0,0,0,0,0,0,0,0,0,0,0,0,0,0,0,0,0,0,0,0,0,0,0,0,0,0,0,0,0,0,0,0,0,0,0,0,0,0,0,0,0,0,0,0,0,0,0,0,0,0,0,0,0,0,0,0,0,0,0,0,0,0,0,0,0,0,0,0,0,0,0,0,0,0,0,0,0,0,0,0,0,0,0,0,0,0,0,0,0,0,0,0,0,0,0,0,0,0,0,0,0,0,0,0,0,0,0,0,0,0,0,0,0,0,0,0,0,0,0,0,0,0,0,0,0,0,0,0,0,0,0,0,0,0,0,0,0,0,0,0,0,0,0,0,0,0,0,0,0,0]}",
      "executable": false,
      "lamports": 4127280,
      "owner": "stkBL96RZkjY5ine4TvPihGqW8UHJfch2cokjAPzV8i",
      "rentEpoch": 371,
      "space": 465
    },
    "pubkey": "75KiJ7mcbikSMVs1uaMKBNucCLG1tTkZkxoQyjYKy4S2",
    "parsed": {
      "bump": "255",
      "identifier": "20",
      "authority": "DnQ7QhZCFhBFsVVFZ36ScLJySMC3NNZyvNfeQtA7G8qC",
      "requiresCreators": "",
      "requiresCollections": "",
      "requiresAuthorization": "false",
      "overlayText": "STAKED",
      "imageUri": "",
      "resetOnStake": "false",
      "totalStaked": "0"
    }
  },
  "rewardDistributor": {
    "timestamp": 1693168017575,
    "pubkey": "CfAQLmtGfa7fNgehRQtzXgtDt2W3RTrDTUnMLv3Y9Kmb",
    "data": "{\"type\":\"Buffer\",\"data\":[215,10,217,199,104,194,97,227,254,90,65,154,61,163,108,129,164,223,18,195,166,230,33,153,214,229,110,150,29,233,134,62,109,169,60,198,41,124,36,88,215,2,189,237,130,185,121,84,62,179,99,176,59,161,10,60,125,8,163,222,87,100,179,49,135,250,136,175,196,21,225,157,77,127,170,116,138,188,113,124,204,49,240,139,11,253,3,101,110,199,2,236,11,193,154,248,97,37,251,202,105,48,189,114,254,234,100,0,0,0,0,0,0,0,1,0,0,0,0,0,0,0,0,0,0,0,0,0,0,0,0,0,0,0,0,0,0,0,0,0,0,0,0,0,0,0,0,1,0,0,0,0,0,0,0,0,0,0,0,0,0,0,0,0,0,0,0,0,0,0,0,0,0,0,0,0,0,0,0,0,0,0,0,0,0,0,0,0,0,0,0,0,0,0,0,0,0,0,0,0,0,0,0,0,0,0,0,0,0,0,0,0,0,0,0,0]}",
    "executable": false,
    "lamports": 2394240,
    "owner": "rwdNPNPS6zNvtF6FMvaxPRjzu2eC51mXaDT9rmWsojp",
    "rentEpoch": 371,
    "space": 216,
    "type": "rewardDistributor",
    "parsed": {
      "bump": "254",
      "stakePool": "75KiJ7mcbikSMVs1uaMKBNucCLG1tTkZkxoQyjYKy4S2",
      "kind": "2",
      "authority": "DnQ7QhZCFhBFsVVFZ36ScLJySMC3NNZyvNfeQtA7G8qC",
      "rewardMint": "CUPNycxUkuhJmY1qiTktY2UwEHHkiferouVyggCd8A1o",
      "rewardAmount": "100",
      "rewardDurationSeconds": "1",
      "rewardsIssued": "0",
      "defaultMultiplier": "1",
      "multiplierDecimals": "0"
    }
  },
  "rewardDistributorTokenAccount": {
    "address": "7P9ra7YkLw6mGzxFMJAYcuwRUBFJVQMir5RzKuDfFJxb",
    "mint": "CUPNycxUkuhJmY1qiTktY2UwEHHkiferouVyggCd8A1o",
    "owner": "CfAQLmtGfa7fNgehRQtzXgtDt2W3RTrDTUnMLv3Y9Kmb",
    "amount": "100",
    "delegate": null,
    "delegatedAmount": "0",
    "isInitialized": true,
    "isFrozen": false,
    "isNative": false,
    "closeAuthority": null,
    "tlvData": {
      "type": "Buffer",
      "data": "[]"
    }
  },
  "stakeEntries": [],
  "rewardEntries": []
}
